zangetsu_data/__init__.py
zangetsu_data/bigquery.py
zangetsu_data/common_database.py
zangetsu_data/postgresql.py
zangetsu_data/settings.py
zangetsu_data/spreadsheet.py
zangetsu_data-0.1.3.dist-info/LICENSE
zangetsu_data-0.1.3.dist-info/METADATA
zangetsu_data-0.1.3.dist-info/WHEEL
zangetsu_data-0.1.3.dist-info/top_level.txt
zangetsu_data-0.1.3.dist-info/RECORD
